Workbook

Sheet Resumen
A1: Matriz de coherencia, brechas y pendientes · PEI CMA · Fase 5
A2: Colegio María Auxiliadora de Soacha · versión v0.2 del 5 de octubre de 2026 · EICIT propone; el Colegio decide y adopta.
A4: Ítems de la plantilla mapeados | B4: =COUNTA(Mapa_plantilla!B5:B39) -> 35
A5: — Ajustados o nuevos en la v0.2 | B5: =COUNTIF(Mapa_plantilla!D5:D39,"Ajustado")+COUNTIF(Mapa_plantilla!D5:D39,"Nuevo") -> 12
A6: — Completos | B6: =COUNTIF(Mapa_plantilla!D5:D39,"Completo") -> 1
A7: — Existen en el 0K (por revisar o condensar) | B7: =COUNTIF(Mapa_plantilla!D5:D39,"Existe")+COUNTIF(Mapa_plantilla!D5:D39,"Por revisar")+COUNTIF(Mapa_plantilla!D5:D39,"Por ajustar") -> 19
A8: — Faltan | B8: =COUNTIF(Mapa_plantilla!D5:D39,"Falta") -> 1
A9: — No aplican (confirmar) | B9: =COUNTIF(Mapa_plantilla!D5:D39,"No aplica") -> 2
A10: Hallazgos registrados | B10: =COUNTA(Hallazgos!A5:A21) -> 17
A11: — Resueltos en la v0.2 | B11: =COUNTIF(Hallazgos!G5:G21,"Resuelto en v0.2") -> 7
A12: — Pendientes de EICIT | B12: =COUNTIF(Hallazgos!G5:G21,"Pendiente EICIT") -> 4
A13: — Pendientes del Colegio | B13: =COUNTIF(Hallazgos!G5:G21,"Pendiente CMA") -> 6
A14: Pendientes de datos y documentos | B14: =COUNTA(Pendientes!A5:A23) -> 19
A15: — Que bloquean la radicación | B15: =COUNTIF(Pendientes!F5:F23,"Bloquea*") -> 5
A16: Páginas actuales / objetivo / límite | B16: =Paginacion!B20&" / "&Paginacion!C20&" / "&Paginacion!C21 -> 92 / 46 / 50
A19: Fuentes: PEICMASEM-0K, Plantilla-Guía SEM 2026-2027, modelo pedagógico validado, arquitectura v5-def (consenso del 30-sep-2026), icfes.pptx, acta n.º 06, convenio EICIT–CMA, Manual de Convivencia, SIEE y Políticas.

Sheet Mapa_plantilla
A1: Mapa de la plantilla de la SEM frente al PEI base (0K) y la v0.2
A2: Estado: Completo · Ajustado · Existe · Por revisar · Por ajustar · Nuevo · Falta · No aplica. Color de «Lidera»: EICIT navy, ENSMA azul medio, Ambas dorado.
A4: Gestión | B4: Ítem de la plantilla SEM | C4: Sección en el 0K | D4: Estado | E4: Observación | F4: Lidera
A5: Identidad | B5: Datos generales | C5: 1.1 | D5: Ajustado | E5: Completados: DANE, NIT, naturaleza, licencia (Res. 001380/1999), niveles, jornada Única, calendario A, representante legal; totales de matrícula 2026 corregidos y proyección 2027 añadida. Falta la autoridad que expidió la licencia. | F5: ENSMA
A6: Identidad | B6: Reseña histórica | C6: 1.2 | D6: Existe | E6: Contenido completo; condensar a 1 página al ajustar la extensión. | F6: ENSMA
A7: Identidad | B7: Emblemas o símbolos (escudo, bandera, himno) | C7: 1.3 | D7: Completo | E7: Escudo, bandera e himno ya están en el 0K (pág. 7). | F7: ENSMA
A8: Gestión Directiva | B8: Caracterización institucional | C8: 2.1 | D8: Existe | E8: Actualizar con Saber 11 de 2026 (hecho en 3.3.3); condensar el diagnóstico externo. | F8: Ambas
A9: Gestión Directiva | B9: Filosofía o fundamentos | C9: 2.2 | D9: Ajustado | E9: Se retiró «software» del fundamento epistemológico; condensar (8 pp). | F9: Ambas
A10: Gestión Directiva | B10: Horizonte (misión, visión, valores, perfiles) | C10: 2.3 | D10: Ajustado | E10: Misión y visión con media técnica en Analítica de Datos y «Nuevos Patios»; lema en portada; perfiles completos (condensar). | F10: ENSMA
A11: Gestión Directiva | B11: Políticas institucionales | C11: 2.4 | D11: Por revisar | E11: El 0K reemplazó dos enlaces por uno; falta contrastar el texto con el PDF «10. Políticas institucionales CMA». | F11: Ambas
A12: Gestión Directiva | B12: Política de inclusión | C12: 2.4.4 | D12: Existe | E12: Coherente con Decreto 1421/2017; verificar enlace. | F12: ENSMA
A13: Gestión Directiva | B13: Gobernanza | C13: 2.6 | D13: Existe | E13: Numeración desfasada (2.6 en lugar de 2.5). | F13: EICIT
A14: Gestión Directiva | B14: Objetivos y metas del PEI | C14: 2.7 | D14: Existe | E14: Subnumeración «9.1, 9.2, 9.3» dentro de 2.7; corregir en la auditoría de numeración. | F14: EICIT
A15: Gestión Académica | B15: Lineamientos de la propuesta pedagógica y curricular | C15: 3.1 | D15: Existe | E15: Dos apartados «3.1»; condensar (6 pp). | F15: EICIT
... A39: Cierre | B39: Referencias bibliográficas y anexos | C39: Anexos A–C | D39: Ajustado | E39: Anexo A (repositorio), B (referentes de la Circular 0064) y C (registro de adopción). | F39: EICIT

Sheet Hallazgos
A1: Hallazgos de coherencia del PEI base (0K) y acciones en la v0.2
A2: Prioridad: Alta · Media · Baja. Estado: Resuelto en v0.2 · Pendiente EICIT · Pendiente CMA.
A4: ID | B4: Prioridad | C4: Ítem | D4: Hallazgo | E4: Evidencia | F4: Acción en v0.2 | G4: Estado | H4: Lidera
A5: H-01 | B5: Alta | C5: Forma | D5: El 0K ocupa unas 93 páginas con interlineado actual y tipografía distinta; la plantilla pide máximo 50 páginas en oficio, fuente 11, interlineado 1.5 y márgenes reflejados, con 1–4 párrafos sugeridos por ítem. | E5: Plantilla SEM; render del 0K | F5: Se documenta el presupuesto de páginas (hoja Paginacion); la condensación y el ajuste de forma son el paso siguiente. | G5: Pendiente EICIT | H5: EICIT
A6: H-02 | B6: Alta | C6: 1.1 Datos generales | D6: El 0K no traía licencia, DANE, NIT, naturaleza jurídica ni calendario en la tabla de datos. | E6: 0K p. 4 | F6: Se insertaron las filas con los datos entregados; licencia: Res. 001380 del 30-nov-1999 (falta autoridad expedidora). | G6: Resuelto en v0.2 | H6: Ambas
A7: H-03 | B7: Alta | C7: Misión, visión, DOFA, fundamentos | D7: El 0K mantenía «programación de software» en 15 lugares frente a la denominación Programación para Analítica de Datos. | E7: PEICMASEM-0K | F7: Reemplazos con control de cambios; se conservan «Software Novasoft» y la pregunta de licencias de software del formulario. | G7: Resuelto en v0.2 | H7: EICIT
A8: H-04 | B8: Media | C8: 1.1 Matrícula 2026 | D8: La fila TOTAL decía 29 cursos y 528 estudiantes; las filas suman 20 cursos y 529 estudiantes. | E8: Tabla de oferta del 0K | F8: Corregido a 20 y 529; se añade la proyección 2027 (21 cursos, 576 estudiantes). | G8: Resuelto en v0.2 | H8: EICIT
A9: H-05 | B9: Media | C9: 1.1 Representante legal | D9: El 0K indicaba a Sor Martha Ortiz con delegada; el dato entregado y el convenio señalan a Bertha Elvira Vivas Mejía. | E9: Convenio EICIT–CMA; mensaje del Coordinador | F9: Se reemplaza el nombre y se elimina la línea de delegada. | G9: Resuelto en v0.2 | H9: Ambas
A10: H-06 | B10: Alta | C10: 4.1 / 3.5 Ley 2394 | D10: El Manual de Convivencia y el SIEE (26-jul-2026) no contienen «2394» ni «gestante»; no hay cláusula de permanencia y no discriminación. | E10: Búsqueda de texto en ambos PDF | F10: Párrafo propuesto en 4.1 con pendiente; EICIT redactará la cláusula para el Manual y el SIEE. | G10: Pendiente CMA | H10: ENSMA
A11: H-07 | B11: Media | C11: Manual de convivencia | D11: El Manual incluye el Capítulo 16 «Reglamento de Residencias Escolares», que no corresponde al Colegio. | E11: Índice del Manual | F11: Se solicita su retiro; no afecta el PEI. | G11: Pendiente CMA | H11: ENSMA
A12: H-08 | B12: Alta | C12: 2.1 / 3.3.3 Saber 11 | D12: Con ICFES 2026 (29 evaluados) el global estimado baja a 298,1 (304,8 en 2025). Matemáticas concentra el 37 % de la caída 2023-2026, Ciencias Naturales el 22 %, Lectura Crítica el 17 %, Sociales y Ciudadanas el 17 % (mejora en 2026) e Inglés el 7 %. | E12: icfes.pptx; matriz 1.2.4 | F12: Tabla 2023-2026 y texto en 3.3.3. La arquitectura se justificó con 2023-2025 (Sociales 2.º factor): el Consejo Académico debe revisar la prioridad. | G12: Pendiente CMA | H12: Ambas
A13: H-09 | B13: Media | C13: 3.3.3 Saber 11 | D13: El reporte del Colegio da un promedio ponderado de 59,88 usando 1,5 para Inglés; la ponderación ICFES del global es 3-3-3-3-1. | E13: icfes.pptx (lámina «Resultados ICFES 2026») | F13: Se muestra el cálculo con ponderación ICFES y se aclara la diferencia en nota al pie. Verificar con el informe oficial del ICFES. | G13: Pendiente EICIT | H13: EICIT
A14: H-10 | B14: Media | C14: Numeración e índice | D14: Numeración irregular: 2.6 por 2.5 y 2.7 con subtítulos 9.x; «3.1» repetido; falta 3.3.3 (ahora cubierto); «3. 5» del SIEE; dos «5.4»; el índice manual no coincide con el paginado. | E14: 0K | F14: Se agregó 3.3.3, 5.2.1 y 5.5.1; la auditoría de numeración y el índice se rehacen al condensar. | G14: Pendiente EICIT | H14: EICIT
A15: H-11 | B15: Baja | C15: Nombre institucional | D15: Mezcla de «Escuela Normal (Superior)» (10 menciones fuera de la historia), «ENSMA» y «Colegio María Auxiliadora». Rector escrito Miryan, Myrian y Myriam según el documento. | E15: 0K; convenio; acta n.º 06 | F15: Unificar nomenclatura en la condensación; confirmar escritura correcta del nombre de la Rectora. | G15: Pendiente CMA | H15: Ambas
... A21: H-17 | B21: Baja | C21: Forma | D21: El 0K usa hoja de 8,5 × 14 pulgadas y Bookman Old Style; la plantilla pide oficio, Times New Roman, Calibri o Arial 11. | E21: document.xml del 0K | F21: Se mantiene el formato del 0K en esta versión; el ajuste de forma va en el paso de condensación. | G21: Pendiente EICIT | H21: EICIT

Sheet Pendientes
A1: Pendientes de datos y documentos para cerrar el PEI
A2: «Bloquea la radicación» = requerido antes de radicar en el SAC de la SEM.
A4: ID | B4: Dato o documento | C4: Ítem | D4: Quién lo aporta | E4: Lidera | F4: Bloqueo | G4: Observación
A5: P-01 | B5: Autoridad que expidió la Resolución 001380 del 30-nov-1999 | C5: 1.1 | D5: Rectoría | E5: ENSMA | F5: No bloquea el borrador; sí la radicación | G5: Basta la referencia (número y fecha); el documento no es necesario para el PEI.
A6: P-02 | B6: Acto administrativo del cambio de denominación y del cierre del Programa de Formación Complementaria | C6: 1.2 | D6: Rectoría | E6: ENSMA | F6: No bloquea el borrador | G6: Citar número y fecha en la reseña.
A7: P-03 | B7: Aval de la SEM a la modificación de licencia para media técnica; oficio del SENA que aprueba la denominación | C7: 1.1; 3.3.3 | D7: Rectoría / SEM | E7: Ambas | F7: No bloquea el borrador | G7: El texto lo presenta como «en trámite».
A8: P-04 | B8: Acta del Consejo Académico que valida el modelo pedagógico | C8: 3.2 | D8: Coordinación Académica | E8: ENSMA | F8: No bloquea el borrador
A9: P-05 | B9: Decisión del Consejo Directivo sobre costos 2027 y resolución rectoral | C9: 5.2 | D9: Consejo Directivo | E9: ENSMA | F9: Bloquea la radicación | G9: Acta n.º 06 legible solo en parte.
A10: P-06 | B10: Decisión sobre validación de grados (Res. 0644/2026) | C10: 5.2.1 | D10: Consejo Directivo | E10: ENSMA | F10: Bloquea la radicación | G10: EICIT redacta propuesta de texto y protocolo.
A11: P-07 | B11: Cláusula Ley 2394/2024 en el Manual de Convivencia y el SIEE | C11: 3.5; 4.1 | D11: Coordinación de Convivencia y Académica | E11: ENSMA | F11: Bloquea la radicación | G11: EICIT redacta la cláusula.
A12: P-08 | B12: Retiro del Capítulo 16 «Reglamento de Residencias Escolares» del Manual | C12: 4.1 | D12: Coordinación de Convivencia | E12: ENSMA | F12: No bloquea
A13: P-09 | B13: Número y fecha del convenio EICIT–CMA; confirmar «sin cobro» | C13: 5.5.1 | D13: Rectoría y EICIT | E13: Ambas | F13: No bloquea el borrador
A14: P-10 | B14: Día y franja de la jornada extendida de 10.° y 11.° (D-11) | C14: 3.3.3 | D14: Rectoría | E14: ENSMA | F14: No bloquea el borrador
A15: P-11 | B15: Tratamiento de la Eucaristía dentro de Educación Religiosa (D-09) | C15: 3.3.3 | D15: Rectoría y Consejo Académico | E15: ENSMA | F15: No bloquea el borrador
A16: P-12 | B16: Brecha de 74 h de la media técnica: gestión ante la SEM o contingencia (D-15) | C16: 3.3.3 | D16: Rectoría | E16: ENSMA | F16: Bloquea la radicación
A17: P-13 | B17: Conciliar 38 y 37 semanas lectivas en el libro de trabajo | C17: 3.3.3 | D17: EICIT y Coordinación Académica | E17: Ambas | F17: No bloquea el borrador
A18: P-14 | B18: Confirmar convenios vigentes con la Universidad Pedagógica, La Salle y la Universidad Salesiana | C18: 4.2 | D18: Rectoría | E18: ENSMA | F18: No bloquea el borrador
A19: P-15 | B19: Planes de estudio de las áreas (146 por elaborar; 12 de Tecnología e Informática a cargo de EICIT) | C19: 3.3.3 | D19: Docentes y EICIT | E19: Ambas | F19: No bloquea el PEI | G19: Se cargan al Drive a medida que avancen.
A20: P-16 | B20: Registro de adopción: proceso con los estamentos, actas de Consejo Académico y Directivo, resolución rectoral y radicado SAC | C20: Anexo C | D20: Rectoría | E20: ENSMA | F20: Bloquea la radicación
A21: P-17 | B21: Confirmar que no ofrece EPJA ni modelos flexibles; verificar el Plan de Formación Integral (PTAFI) | C21: 3.3 | D21: Coordinación Académica | E21: Ambas | F21: No bloquea el borrador
A22: P-18 | B22: Escritura correcta del nombre de la Rectora (Miryan / Myrian / Myriam) | C22: 1.1 | D22: Rectoría | E22: ENSMA | F22: No bloquea el borrador
A23: P-19 | B23: Confirmar asignatura de Infancia Misionera y Educación Emocional en la tabla de proyectos | C23: 3.3.4 | D23: EICIT | E23: EICIT | F23: No bloquea el borrador

Sheet Paginacion
A1: Presupuesto de páginas para cumplir la plantilla (máximo 50)
A2: Actual: páginas aproximadas de la v0.2 (render con tipografía sustituta). Objetivo: formato final (oficio, fuente 11, interlineado 1.5). El resto se reubica en el repositorio (Drive, modo lector).
A4: Sección | B4: Páginas actuales (v0.2) | C4: Páginas objetivo | D4: Diferencia
A5: Portada, presentación e índice | B5: 3 | C5: 2 | D5: =C5-B5 -> -1
A6: 1. Identidad institucional | B6: 5 | C6: 3 | D6: =C6-B6 -> -2
A7: 2.1 Caracterización | B7: 8 | C7: 3 | D7: =C7-B7 -> -5
A8: 2.2 Filosofía y fundamentos | B8: 8 | C8: 2 | D8: =C8-B8 -> -6
A9: 2.3 Horizonte | B9: 1 | C9: 1 | D9: =C9-B9 -> 0
A10: Perfiles institucionales | B10: 9 | C10: 2 | D10: =C10-B10 -> -7
A11: 2.4 Políticas | B11: 2 | C11: 1.5 | D11: =C11-B11 -> -0.5
A12: 2.6–2.7 Gobernanza, objetivos y metas | B12: 3 | C12: 2.5 | D12: =C12-B12 -> -0.5
A13: 3.1 Lineamientos | B13: 6 | C13: 1.5 | D13: =C13-B13 -> -4.5
A14: 3.2 Modelo pedagógico | B14: 12 | C14: 3 | D14: =C14-B14 -> -9
A15: 3.3 Planes de estudio (arquitectura 2027) | B15: 4 | C15: 5 | D15: =C15-B15 -> 1
A16: 3.4–3.5 Proyectos y SIEE | B16: 3 | C16: 2.5 | D16: =C16-B16 -> -0.5
... A19: Referencias, anexos A–C | B19: 4 | C19: 3 | D19: =C19-B19 -> -1
A20: TOTAL | B20: =SUM(B5:B19) -> 92 | C20: =SUM(C5:C19) -> 46 | D20: =SUM(D5:D19) -> -46
A21: Límite de la plantilla SEM | C21: 50
A22: Margen frente al límite | C22: =C21-C20 -> 4
A24: Supuesto: el objetivo por sección es una propuesta de EICIT para decisión del Colegio; se calculó para que el total quede por debajo de 50 páginas en el formato final.
