Workbook

Sheet Portada
B2: EICIT · Escuela Iberoamericana de Ciencias Técnicas
B4: Revisión de la Autoevaluación Institucional (Guía 34)
B5: Insumo para el transverso de calidad del PEI 2026–2027 · ENSMA
B6: ESTRUCTURA DE TRABAJO — lista para cargar y concluir
B8: Tarea del cronograma | C8: 1.2.4 — Revisión de la autoevaluación
B9: Marco | C9: Guía 34 (MEN) · Circular 0064 de 2026 (SEM) · PEI 2026–2027
B10: Fuente autoevaluación | C10: Autoevaluación Procesos Institucionales Guía 34 – 2026 I (I semestre 2026)
B11: Alcance | C11: 6 procesos SGC · 96 componentes · escala 1–4
B12: Estado | C12: Cargado: I-2026 + evidencia externa (Saber 11, matrícula). PENDIENTE: ciclo anterior (2025).
B13: Elaboró | C13: EICIT IA — asistencia técnica
B14: Encuadre | C14: EICIT propone y revisa; la autoevaluación es de la ENSMA, que delibera y adopta.
B16: Cómo está construida
B17: • Matriz_Revisión: las 96 filas ya vienen con proceso, componente y autovaloración I-2026 precargados.
B18: • Columna «Val. ciclo anterior (2025)» en naranja = lo único por diligenciar cuando ENSMA entregue el insumo.
B19: • La «Tendencia» se calcula sola al cargar el 2025; luego se concluye Coherencia, cotejo con PMI y Prioridad.
B20: • Evidencia_Externa y Tablero ya están cargados; Transverso_Calidad es el esqueleto del cuadro de mando.

Sheet Matriz_Revisión
A1: Proceso (SGC) | B1: Gestión (Guía 34) | C1: Subproceso | D1: Componente | E1: Val. ciclo anterior (2025) | F1: Val. I-2026 | G1: Tendencia | H1: Evidencia declarada (resumen) | I1: Triangulación externa | J1: Coherencia autoval.↔evidencia | K1: Oportunidad de mejora (instrumento) | L1: ¿Acción en PMI? | M1: Prioridad
A2: PROCESO DIRECTIVO → Gestión Directiva (25 componentes)
A3: DIRECTIVO | B3: Directiva | C3: Direccionamiento estratégico y horizonte institucional | D3: Conocimiento y apropiación de la Misión, Visión y Política de Calidad | F3: 4 | G3: =IF(E3="","—",IF(F3>E3,"▲",IF(F3<E3,"▼","="))) -> — | H3: Se cuenta con evidencias documentales y prácticas que demuestran la apropiación del horizonte institucional, tales como: los planes operativos y de me… | I3: Matrícula 803→425→503 (2015–24); transición de identidad (Normal→EPBM/técnica). | K3: Aunque se evidencia una apropiación significativa del horizonte institucional, es conveniente fortalecer los mecanismos de evaluación del impacto de las estrategias implementadas, ampliar los espacios…
A4: DIRECTIVO | B4: Directiva | C4: Direccionamiento estratégico y horizonte institucional | D4: Conocimiento y apropiación de los Objetivos institucionales | F4: 3 | G4: =IF(E4="","—",IF(F4>E4,"▲",IF(F4<E4,"▼","="))) -> — | H4: Los objetivos institucionales se encuentran consignados en el PEI, en algunas carteleras Asimismo, existen registros de capacitaciones, reuniones, jor… | I4: Matrícula 803→425→503 (2015–24); transición de identidad (Normal→EPBM/técnica). | K4: Fortalecer las estrategias de sensibilización y seguimiento para garantizar una mayor apropiación de los objetivos institucionales por parte de todos los miembros de la comunidad educativa. Asimismo, …
A5: DIRECTIVO | B5: Directiva | C5: Direccionamiento estratégico y horizonte institucional | D5: Conocimiento y apropiación de la filosofía educativa salesiana: Principios y Fundamentos del Sistema Preventivo de Don Bosco | F5: 4 | G5: =IF(E5="","—",IF(F5>E5,"▲",IF(F5<E5,"▼","="))) -> — | H5: Actas de ReuniónTriduo escolarManual de ConvivenciaAguinaldo del Rector mayor Capacitación: Formación conjunta. retiros espirituales por grado | K5: Continuar acompañando a toda la comunidad educativa de la institución para la vivencia del sistema preventivo y el aguinaldo del rector mayor.Tener presente que criterios se van a evaluar de acuerdo a…
A6: DIRECTIVO | B6: Directiva | C6: Direccionamiento estratégico y horizonte institucional | D6: Política de inclusión de estudiantes con capacidades disímiles o diversidad cultural | F6: 4 | G6: =IF(E6="","—",IF(F6>E6,"▲",IF(F6<E6,"▼","="))) -> — | H6: La cartelera informativa ENSUMAUXI inclusiva tercer piso. Acta reunión de consejo académico. Acta de Equipo Pastoral Actas de Reunión de Docentescapac… | I6: Matrícula 803→425→503 (2015–24); transición de identidad (Normal→EPBM/técnica). | K6: Fortalecer la apropiación de la política de educación inclusiva y de la normatividad vigente (Decreto 1421 de 2017 y Decreto 2216 de 2022), con el fin de consolidar estrategias integrales que responda…
A7: DIRECTIVO | B7: Directiva | C7: Gestión estratégica | D7: Liderazgo y criterios claros en el direccionamiento de la ENS | F7: 4 | G7: =IF(E7="","—",IF(F7>E7,"▲",IF(F7<E7,"▼","="))) -> — | H7: PEI y actas de reuniones del consejo académico, resultados de autoevaluaciones institucionales que están en el drive.Estos permiten verificar la plane… | K7: Fortalecer la sistematización y socialización de los acuerdos, decisiones y resultados derivados de las reuniones y autoevaluaciones, de manera que toda la comunidad educativa conozca los avances y co…
A8: DIRECTIVO | B8: Directiva | C8: Gestión estratégica | D8: Seguimiento y evaluación adecuada y oportuna de las actividades programadas y realizadas en la institución | F8: 3 | G8: =IF(E8="","—",IF(F8>E8,"▲",IF(F8<E8,"▼","="))) -> — | H8: Resultados de las evaluaciones aplicadas a las diferentes actividades institucionales desarrolladas con los cursos, los cuales permiten evidenciar el … | K8: Establecer estrategias de retroalimentación que permitan socializar los hallazgos de cada una de las actividades y definiendo de manera concreta las acciones de mejora.
A9: DIRECTIVO | B9: Directiva | C9: Gobierno escolar | D9: Organización y funcionamiento del Consejo Directivo | F9: 4 | G9: =IF(E9="","—",IF(F9>E9,"▲",IF(F9<E9,"▼","="))) -> — | H9: Acta de conformación Actas de reuniones | K9: Se recomienda dar continuidad a la gestión del Consejo Directivo mediante el seguimiento permanente de los temas abordados, el cumplimiento de los compromisos adquiridos y el avance efectivo de las ac…
A10: DIRECTIVO | B10: Directiva | C10: Gobierno escolar | D10: Organización y funcionamiento del Consejo Académico | F10: 4 | G10: =IF(E10="","—",IF(F10>E10,"▲",IF(F10<E10,"▼","="))) -> — | H10: Acta de conformación y actas de reuniones | K10: Continuar fortaleciendo este proceso, avanzando en pro de una gestión cada vez más eficiente y con miras a la mejora continua
A11: DIRECTIVO | B11: Directiva | C11: Gobierno escolar | D11: Organización y funcionamiento de las Comisiones de Evaluación y Promoción | F11: 4 | G11: =IF(E11="","—",IF(F11>E11,"▲",IF(F11<E11,"▼","="))) -> — | H11: Acta de conformación y actas de comisión y consolidado de notas | K11: Mayor exigencia y compromiso por parte de docentes en todo el proceso de pre-comisión y comisión, con el fin de contar con los soportes necesarios para poder proponer estrategias de mejora a casos esp…
A12: DIRECTIVO | B12: Directiva | C12: Gobierno escolar | D12: Organización y funcionamiento del Consejo Estudiantil | F12: 4 | G12: =IF(E12="","—",IF(F12>E12,"▲",IF(F12<E12,"▼","="))) -> — | H12: Acta de conformaciónActa izada de Banderas Posesión consejos estudiantil.Material visual en la carpeta de evidencias del área de Ciencias Sociales. | K12: Fortalecer el conocimiento y la apropiación de las funciones y responsabilidades de los integrantes del Consejo Estudiantil, con el fin de potenciar y visibilizar su liderazgo dentro de la comunidad e…
A13: DIRECTIVO | B13: Directiva | C13: Gobierno escolar | D13: Desempeño de la Personera de Estudiantes | F13: 3 | G13: =IF(E13="","—",IF(F13>E13,"▲",IF(F13<E13,"▼","="))) -> — | H13: Acta de posesiónHojas de vida Propuestas de gobiernoActa No 1 de izada de banderaActas de reuniones de consejo estudiantes y directivoParticipación co… | K13: Continuar trabajando con compromiso y responsabilidad para que sus propuestas se lleven a cabo para el beneficio de la comunidad estudiantil.
A14: DIRECTIVO | B14: Directiva | C14: Gobierno escolar | D14: Organización y realización de las reuniones con los Padres de familia | F14: 4 | G14: =IF(E14="","—",IF(F14>E14,"▲",IF(F14<E14,"▼","="))) -> — | H14: Acta de conformaciónLink de asistencia | K14: Continuar con la promoción de la importancia de asistencia a escuela de padres
A15: DIRECTIVO | B15: Directiva | C15: Gobierno escolar | D15: Organización y funcionamiento del Consejo de Padres de Familia. | F15: 3 | G15: =IF(E15="","—",IF(F15>E15,"▲",IF(F15<E15,"▼","="))) -> — | H15: Actas mensuales de reuniones del Consejo de Padres de Familia. | K15: Mayor compromiso por parte de los padres de familia en cuanto a la asistencia, asegurando la asistencia del titular o del suplente, para poder dar un buen orden a la reunión. Hacer seguimiento a los c…
A16: DIRECTIVO | B16: Directiva | C16: Cultura institucional | D16: Uso apropiado y oportuno de los Mecanismos de comunicación interna y externa | F16: 3 | G16: =IF(E16="","—",IF(F16>E16,"▲",IF(F16<E16,"▼","="))) -> — | H16: Se implementan medios físicos y virtuales, como lo son: agenda escolar, correos institucionales, plataforma (pegasus), teléfono institucional, redes s… | K16: Realizar una revisión periódica y oportuna de todos los medios de comunicación establecidos por la institución, tales como la agenda estudiantil, correos electrónicos, plataformas institucionales, cir…
A17: DIRECTIVO | B17: Directiva | C17: Cultura institucional | D17: Ambiente de trabajo colaborativo y en equipo | F17: 3 | G17: =IF(E17="","—",IF(F17>E17,"▲",IF(F17<E17,"▼","="))) -> — | H17: Se realizan diferentes encuentros de integración y socialización que ayudan y promueven el trabajo en equipo y la colaboración. Esto liderado por el c… | K17: Continuar fortaleciendo y ampliando los espacios de integración y socialización, promoviendo una mayor participación de todos los miembros de la comunidad educativa para consolidar el trabajo en equip…
A18: DIRECTIVO | B18: Directiva | C18: Cultura institucional | D18: Divulgación de las buenas prácticas educativas y de experiencias pedagógicas, significativas | F18: 4 | G18: =IF(E18="","—",IF(F18>E18,"▲",IF(F18<E18,"▼","="))) -> — | H18: La institución divulga información a través de redes sociales, boletines informativos y encuentros presenciales con la comunidad educativa, garantizan… | K18: Fortalecer el uso y alcance de las redes sociales institucionales como medio de divulgación de las actividades, proyectos y logros de la comunidad educativa, promoviendo una mayor participación e inte…
... A27: DIRECTIVO | B27: Directiva | C27: Relaciones con el entorno. | D27: Relaciones con el Sector Productivo | F27: 4 | G27: =IF(E27="","—",IF(F27>E27,"▲",IF(F27<E27,"▼","="))) -> — | H27: Se están articulando y estableciendo alianzas estratégicas con universidades,sector productivo y otras entidades con el propósito de fortalecer los pr… | K27: Continuar fortaleciendo los procesos de articulación entre la formación académica, técnica y las necesidades del entorno laboral.
A28: PROCESO ACADÉMICO PEDAGÓGICO → Gestión Académica (24 componentes)
A29: ACADÉMICO PEDAGÓGICO | B29: Académica | C29: Diseño Curricular | D29: Conocimiento, desarrollo y aplicación de la Estructura Curricular (formas 1, 2 y 3) y del Plan de estudios. | F29: 4 | G29: =IF(E29="","—",IF(F29>E29,"▲",IF(F29<E29,"▼","="))) -> — | H29: Se cuenta con las estructuras y formatos institucionales organizados por áreas en Drive. | K29: Continuar fortaleciendo el uso responsable y la actualización oportuna de estos instrumentos en el desarrollo del proceso académico.
A30: ACADÉMICO PEDAGÓGICO | B30: Académica | C30: Diseño Curricular | D30: Organización, desarrollo y articulación en el aula de los proyectos transversales. | F30: 3 | G30: =IF(E30="","—",IF(F30>E30,"▲",IF(F30<E30,"▼","="))) -> — | H30: Se cuenta con el documento y el formato F3 que registran la planeación de actividades de los proyectos transversales. | K30: Continuar llevando al aula las actividades propuestas para fortalecer el aprendizaje y la apropiación de los proyectos por parte de los estudiantes.
A31: ACADÉMICO PEDAGÓGICO | B31: Académica | C31: Diseño Curricular | D31: Conocimiento y aplicación en el aula de la estrategia pedagógica del Constructivismo y Aprendizaje Significativo. | F31: 4 | G31: =IF(E31="","—",IF(F31>E31,"▲",IF(F31<E31,"▼","="))) -> — | H31: En la Forma 3 se evidencia claramente mediante la secuencia didáctica establecida. | K31: Se sugiere dar continuidad a estas prácticas para asegurar y fortalecer la calidad educativa.
A32: ACADÉMICO PEDAGÓGICO | B32: Académica | C32: Diseño Curricular | D32: Uso apropiado de recursos didácticos virtuales y materiales para mejorar el aprendizaje. | F32: 2 | G32: =IF(E32="","—",IF(F32>E32,"▲",IF(F32<E32,"▼","="))) -> — | H32: Se busca la implementación desde la planeación en la F3. | I32: Coincide con línea base 1.2.5: aula virtual y creación con TIC son los ítems más bajos. | K32: Se deben priorizar la generación de espacios físicos y herramientas que promuevan el uso de las TICs.
A33: ACADÉMICO PEDAGÓGICO | B33: Académica | C33: Diseño Curricular | D33: Cumplimiento y provecho de la Jornada escolar. | F33: 4 | G33: =IF(E33="","—",IF(F33>E33,"▲",IF(F33<E33,"▼","="))) -> — | H33: Registro de inicio de jornada, llegadas tarde, información semanal de actividades a destacar y cronograma institucional. | K33: Estar atentos a las actualizaciones de los diferentes informes.
A34: ACADÉMICO PEDAGÓGICO | B34: Académica | C34: Diseño Curricular | D34: Conocimiento y aplicación del Sistema Institucional de Evaluación del Aprendizaje y de la Matriz de Evaluación Integral según nuevos ajustes. | F34: 4 | G34: =IF(E34="","—",IF(F34>E34,"▲",IF(F34<E34,"▼","="))) -> — | H34: Se evidencia en la plataforma educativa Pegasus y las planillas físicas. En el PMI. En las formas 4 mediante plan de mejora. | I34: Saber 11: −19,8 pts (2023–2025), caída en todas las áreas; foco C. Naturales y Sociales. | K34: Continuar con la formación y aplicación del SIEE.
A35: ACADÉMICO PEDAGÓGICO | B35: Académica | C35: Desempeño docente de la práctica pedagógica en el aula. | D35: Asignación de tareas dosificadas que facilitan: la profundización, complementación, asimilación y aplicación de los conocimientos trabajados en clase. | F35: 3 | G35: =IF(E35="","—",IF(F35>E35,"▲",IF(F35<E35,"▼","="))) -> — | H35: Se evidencia en las formas 3, y así mismo en el cronograma de tareas por curso. | K35: Continuar fortaleciendo el objetivo de las tareas en casa..
A36: ACADÉMICO PEDAGÓGICO | B36: Académica | C36: Desempeño docente de la práctica pedagógica en el aula. | D36: Empleo responsable y apropiado del tiempo de clase para mejorar el aprendizaje. | F36: 4 | G36: =IF(E36="","—",IF(F36>E36,"▲",IF(F36<E36,"▼","="))) -> — | H36: Trazabilidad con forma 3, cuadernos, planillas y observaciones de clase. | K36: Continuar trabajando y fortaleciendo los procesos del empleo responsable y apropiado del tiempo de clase para mejorar el aprendizaje.
A37: ACADÉMICO PEDAGÓGICO | B37: Académica | C37: Desempeño docente de la práctica pedagógica en el aula. | D37: Implementar la cultura de la Investigación en el aula, para un mejor aprendizaje. | F37: 2 | G37: =IF(E37="","—",IF(F37>E37,"▲",IF(F37<E37,"▼","="))) -> — | H37: Predomina la mecanización de las clases, con énfasis en lo formal, dejando en segundo plano actividades de exploración como el trabajo de campo. | K37: Incentivar a los docentes a promover la transversalidad desde las diferentes áreas, fortaleciendo la cultura investigativa.
A38: ACADÉMICO PEDAGÓGICO | B38: Académica | C38: Desempeño docente de la práctica pedagógica en el aula. | D38: Planeación y preparación apropiada de las clases periódicamente según la estructura curricular. | F38: 4 | G38: =IF(E38="","—",IF(F38>E38,"▲",IF(F38<E38,"▼","="))) -> — | H38: Se puede evidenciar en las formas 3, seguimiento de trabajo en clase. | K38: Continuar con el proceso de la planeación y preparación apropiada de las clases periódicamente según la estructura curricular.
A39: ACADÉMICO PEDAGÓGICO | B39: Académica | C39: Gestión en el aula | D39: Aplicación de estrategias pedagógicas para mejorar el aprendizaje en el aula y motivar al alcance de la excelencia. | F39: 3 | G39: =IF(E39="","—",IF(F39>E39,"▲",IF(F39<E39,"▼","="))) -> — | H39: La excelencia académica en las asignaturas. | K39: Motivar e implementar estrategias pedagógicas innovadoras y didácticas, lúdicas.
A40: ACADÉMICO PEDAGÓGICO | B40: Académica | C40: Gestión en el aula | D40: Aplicación de diversas estrategias de Evaluación del aprendizaje según la planeación de las formas. tres | F40: 4 | G40: =IF(E40="","—",IF(F40>E40,"▲",IF(F40<E40,"▼","="))) -> — | H40: Se evidencia en la Forma 3, a través del seguimiento al trabajo desarrollado en clase. | I40: Saber 11: −19,8 pts (2023–2025), caída en todas las áreas; foco C. Naturales y Sociales. | K40: Se recomienda continuar fortaleciendo la elaboración y aplicación de diferentes tipos de evaluación.
A41: ACADÉMICO PEDAGÓGICO | B41: Académica | C41: Gestión en el aula | D41: Uso pedagógico de los resultados de las evaluaciones del conocimiento en el aula, para mejorar el aprendizaje de los estudiantes. | F41: 4 | G41: =IF(E41="","—",IF(F41>E41,"▲",IF(F41<E41,"▼","="))) -> — | H41: Se puede evidenciar en las actas de consejo académico, en las formas 4.Los resultados de icfes de la entidad que lo realiza. | I41: Saber 11: −19,8 pts (2023–2025), caída en todas las áreas; foco C. Naturales y Sociales. | K41: Continuar con la generación de estrategias que permitan un análisis exhaustivo de las evaluaciones de conocimiento en el aula.
A42: ACADÉMICO PEDAGÓGICO | B42: Académica | C42: Seguimiento y acompañamiento académico | D42: Uso pedagógico de los resultados de las evaluaciones externas (Estado), para mejorar el aprendizaje en el aula. | F42: 4 | G42: =IF(E42="","—",IF(F42>E42,"▲",IF(F42<E42,"▼","="))) -> — | H42: Se realiza revisión y socialización desde consejo académico de los resultados de las pruebas externas anualmente | I42: Saber 11: −19,8 pts (2023–2025), caída en todas las áreas; foco C. Naturales y Sociales. | K42: Continuar realizando la socialización de las pruebas externas con el fin de que en cada área se puedan implementar las estrategías de mejora pertinentes.
A43: ACADÉMICO PEDAGÓGICO | B43: Académica | C43: Seguimiento y acompañamiento académico | D43: Control y seguimiento de asistencia a clase de estudiantes, por educadores y coordinación. | F43: 4 | G43: =IF(E43="","—",IF(F43>E43,"▲",IF(F43<E43,"▼","="))) -> — | H43: Se cuenta con evidencia en las planillas de asistencia de cada docente, así como en la agenda de portería, donde se registra diariamente la inasistenc… | I43: Saber 11: −19,8 pts (2023–2025), caída en todas las áreas; foco C. Naturales y Sociales. | K43: Se considera fundamental mantener la rigurosidad en el manejo de las inasistencias para garantizar la efectividad del proceso; adicionalmente, se sugiere implementar una estrategia virtual de control …
A44: ACADÉMICO PEDAGÓGICO | B44: Académica | C44: Seguimiento y acompañamiento académico | D44: Reconocimiento y estímulos a estudiantes que sobresalen en su formación integral. | F44: 4 | G44: =IF(E44="","—",IF(F44>E44,"▲",IF(F44<E44,"▼","="))) -> — | H44: Los estudiantes que sobresalen en su formación integral quedan en cuadro de honor y este es visible, además se entrega a los estudiantes un reconocimi… | K44: Pensar en otro reconocimiento para premiar a los estudiantes por su formación integral y tener en cuenta los estudiantes que alcanzan el nivel alto o superior en cuarto periodo para dar su respectivo …
A45: ACADÉMICO PEDAGÓGICO | B45: Académica | C45: Seguimiento y acompañamiento académico | D45: Seguimiento y acompañamiento pedagógico en el aula, a estudiantes con desempeño bajo por debilidades académicas y/o formativas. | F45: 4 | G45: =IF(E45="","—",IF(F45>E45,"▲",IF(F45<E45,"▼","="))) -> — | H45: Los docentes realizan seguimiento y acompañamiento procesual a los estudiantes con desempeño bajo y se cita acudiente para informar. Se registra en el… | I45: Saber 11: −19,8 pts (2023–2025), caída en todas las áreas; foco C. Naturales y Sociales. | K45: Aunque se hace un proceso, en ocasiones se cita a los padres de familia sobre el tiempo, finalizando el periodo, lo que impide que la familia esté con mayor acompañamiento tiempo antes.
A46: ACADÉMICO PEDAGÓGICO | B46: Académica | C46: Seguimiento y acompañamiento académico | D46: Seguimiento y acompañamiento por Coordinación y Psico-orientación a estudiantes con debilidades especiales, académicas y/o formativas. | F46: 4 | G46: =IF(E46="","—",IF(F46>E46,"▲",IF(F46<E46,"▼","="))) -> — | H46: Los registros de los encuentros se consignan en el observador del estudiante, en las agendas y en la plataforma Pegasus. | I46: Saber 11: −19,8 pts (2023–2025), caída en todas las áreas; foco C. Naturales y Sociales. | K46: Se recomienda fortalecer estrategias de acompañamiento con las familias y dar continuidad al seguimiento de los estudiantes con PIAR.
A47: ACADÉMICO PEDAGÓGICO | B47: Académica | C47: Seguimiento y acompañamiento académico | D47: Organización y realización de seguimiento y encuentros de egresadas. | F47: 2 | G47: =IF(E47="","—",IF(F47>E47,"▲",IF(F47<E47,"▼","="))) -> — | H47: Se realiza seguimiento a los estudiantes egresados mediante una base de datos actualizada periódicamente y la organización de un cronograma anual de e… | I47: Saber 11: −19,8 pts (2023–2025), caída en todas las áreas; foco C. Naturales y Sociales. | K47: Se recomienda implementar estrategias que fortalezcan la vinculación de los egresados, promoviendo una mayor participación e incluyendo incentivos que favorezcan su asistencia.
A48: ACADÉMICO PEDAGÓGICO | B48: Académica | C48: Seguimiento y acompañamiento académico | D48: Orientación y acompañamiento por coordinación y maestros orientadores, a los estudiantes del PFC (Programa de Formación Complementaria), en el proceso formativo según el plan de estudios y en su desempeño en la práctica docente. | F48: 4 | G48: =IF(E48="","—",IF(F48>E48,"▲",IF(F48<E48,"▼","="))) -> — | H48: Està evidenciado en los contenidos programàticos del PFC y carpetas propias de la coordinaciòn de investigaciòn | I48: Saber 11: −19,8 pts (2023–2025), caída en todas las áreas; foco C. Naturales y Sociales. | K48: Continuar fortaleciendo la apropiación de los contenidos de clase y el contenido propio de los proyectos de investigación por parte de las maestras de formación..
A49: ACADÉMICO PEDAGÓGICO | B49: Académica | C49: Seguimiento y acompañamiento académico | D49: Orientación de la Investigación Educativa como eje transversal del Programa de Formación Complementaria. | F49: 4 | G49: =IF(E49="","—",IF(F49>E49,"▲",IF(F49<E49,"▼","="))) -> — | H49: Esta evidenciado en los contenidos programàticos del PFC y carpetas propias de la coordinaciòn de investigaciòn | K49: Continuar fortaleciendo la apropiación de los contenidos de clase y el contenido propio de los proyectos de investigación por parte de las maestras de formación..
A50: ACADÉMICO PEDAGÓGICO | B50: Académica | C50: Investigación educativa | D50: Orientación de la Práctica Educativa Investigativa Integral (PEII), en la Media Académica (10° y 11°) y Programa de Formación Complementaria | F50: 4 | G50: =IF(E50="","—",IF(F50>E50,"▲",IF(F50<E50,"▼","="))) -> — | H50: Se evidencia en las planeaciones de clase, estructura curricular y contenido programàticos del PFC. | K50: Continuar fortaleciendo la planeación, seguimiento y evaluación de los proyectos de investigación, 10º, 11º y PFC.
A51: ACADÉMICO PEDAGÓGICO | B51: Académica | C51: Investigación educativa | D51: Organización, ejecución y asesorías a maestros en formación, docentes que orientan los semilleros y PPA , para el desarrollo y avance de los mismos . | F51: 4 | G51: =IF(E51="","—",IF(F51>E51,"▲",IF(F51<E51,"▼","="))) -> — | H51: Se encuentra ubicado en la carpeta del Drive de la coordinacoiòn de investigaciòn | K51: Continuar fortaleciendo los espacios de encuentro y ejecución de los semilleros, PPA y proyectos de investigación.
A52: ACADÉMICO PEDAGÓGICO | B52: Académica | C52: Investigación educativa | D52: Avances en el desarrollo de proyectos de Investigación educativa, trabajados por maestros en formación, y equipos de áreas. | F52: 4 | G52: =IF(E52="","—",IF(F52>E52,"▲",IF(F52<E52,"▼","="))) -> — | H52: Se encuentra relacionado en las carpetas de investigación ubicadas en el drive institucional. | K52: Continuar fortaleciendo las asesorìas y garantizar los espacios pertinentes y el buen aprovechamiento del tiempo, tanto de los estudiantes como del asesor. Respetar los espacios de las asesorìas, evit…
A53: PROCESO ADMINISTRATIVO FINANCIERO → Gestión Administrativa y Financiera (20 componentes)
A54: ADMINISTRATIVO FINANCIERO | B54: Administrativa y Financiera | C54: Apoyo a la gestión académica | D54: Organización y realización de los procesos de Admisión y de Matrículas | F54: 4 | G54: =IF(E54="","—",IF(F54>E54,"▲",IF(F54<E54,"▼","="))) -> — | H54: Se encuentran las carpetas de matrículas rotuladas y protegidas. | K54: Continuar exigiendo el correcto cumplimiento de la entrega de la documentación de los estudiantes.
A55: ADMINISTRATIVO FINANCIERO | B55: Administrativa y Financiera | C55: Apoyo a la gestión académica | D55: Manejo correcto del archivo académico en Secretaría, y de las planillas por educadores. | F55: 3 | G55: =IF(E55="","—",IF(F55>E55,"▲",IF(F55<E55,"▼","="))) -> — | H55: Desde secretaría se realiza el ajuste con los tiempos estipulados para el correcto proceso de digitacion de notas por periodo.Desde coordinación acadé… | K55: Se sugiere configuración adicional en la plataforma PEGASUS para que se notifique al educador cuando una celda quede en blanco a fin de mitigar errores.
A56: ADMINISTRATIVO FINANCIERO | B56: Administrativa y Financiera | C56: Apoyo a la gestión académica | D56: Manejo correcto de los informes de calificaciones, por periodos. | F56: 4 | G56: =IF(E56="","—",IF(F56>E56,"▲",IF(F56<E56,"▼","="))) -> — | H56: Al finalizar el periodo se realiza el envío del informe de calificaciones del periodo académico a través de PEGASUS, a padres, acudientes y estudiante… | K56: Se recomienda fortalecer el proceso de actualización de datos de contacto de los padres de familia, especialmente los correos electrónicos registrados para notificaciones. En algunos casos, la informa…
A57: ADMINISTRATIVO FINANCIERO | B57: Administrativa y Financiera | C57: Administración de la planta física y de los recursos físicos y financieros | D57: Mantenimiento, reparaciones y adecuación de la planta física | F57: 3 | G57: =IF(E57="","—",IF(F57>E57,"▲",IF(F57<E57,"▼","="))) -> — | H57: Los mantenimientos preventivos y correctivos de la planta física se ejecutan de acuerdo con el procedimiento establecido y el cronograma definido por … | K57: Continuar en las mejoras a los requerimientos de reparación.Continuar mejorando los tiempos de respuestas de las reparaciones correctivas asociados a los equipos de cómputo.Continuar en la entrega for…
A58: ADMINISTRATIVO FINANCIERO | B58: Administrativa y Financiera | C58: Administración de la planta física y de los recursos físicos y financieros | D58: Cuidado del ambiente físico y del orden, embellecimiento y uso adecuado de los espacios de la planta física. | F58: 4 | G58: =IF(E58="","—",IF(F58>E58,"▲",IF(F58<E58,"▼","="))) -> — | H58: Se destinan y ejecutan recursos para mantener el embellecimiento de la planta física (facturas).Se motiva a la Comunidad Educativa el cuidado de los e… | K58: Dar continuidad a las acciones de mantenimiento, conservación y cuidado integral en los diferentes espacios de la infraestructura física
A59: ADMINISTRATIVO FINANCIERO | B59: Administrativa y Financiera | C59: Administración de la planta física y de los recursos físicos y financieros | D59: Suministro y dotación apropiada, de equipos y recursos materiales y didácticos; y el uso cuidadoso de estos. | F59: 4 | G59: =IF(E59="","—",IF(F59>E59,"▲",IF(F59<E59,"▼","="))) -> — | H59: Se cuenta con espacios, equipos, recursos y materiales apropiados, para el adecuado funcionamiento de la institución; salones, salas especializadas, p… | K59: Continuar garantizando la provisión continua de dotaciones, materiales e insumos necesarios para el adecuado desarrollo de las actividades institucionales y el óptimo funcionamiento de la comunidad ed…
A60: ADMINISTRATIVO FINANCIERO | B60: Administrativa y Financiera | C60: Administración de la planta física y de los recursos físicos y financieros | D60: Mantenimiento y reparación oportuna, de equipos y recursos didácticos y materiales para el aprendizaje | F60: 4 | G60: =IF(E60="","—",IF(F60>E60,"▲",IF(F60<E60,"▼","="))) -> — | H60: En la oficina de Pagaduría se mantiene permanentemente el formato de solicitud de mantenimiento y reparaciones de los equipos, materiales y recursos. | I60: Coincide con línea base 1.2.5: aula virtual y creación con TIC son los ítems más bajos. | K60: Continuar fortaleciendo y agilizando los4 procesos de mantenimiento y reparación de los equipos de cómputo, con el fin de garantizar su disponibilidad y ofrecer un servicio oportuno y de calidad a los…
A61: ADMINISTRATIVO FINANCIERO | B61: Administrativa y Financiera | C61: Administración de la planta física y de los recursos físicos y financieros | D61: Seguridad y protección del personal que labora. | F61: 4 | G61: =IF(E61="","—",IF(F61>E61,"▲",IF(F61<E61,"▼","="))) -> — | H61: Las instalaciones y espacios cumplen con la normativa de seguridad y salud en el trabajo para todo el personal. | K61: Dar continuidad a la implementación y cumplimiento de los lineamientos establecidos en el Sistema de Gestión de Seguridad y Salud en el Trabajo, conforme a la normativa vigente.
A62: ADMINISTRATIVO FINANCIERO | B62: Administrativa y Financiera | C62: Administración de la planta física y de los recursos físicos y financieros | D62: Promoción de la sana convivencia laboral. | F62: 4 | G62: =IF(E62="","—",IF(F62>E62,"▲",IF(F62<E62,"▼","="))) -> — | H62: Se cuenta con un equipo interinstitucional del comité de convivencia laboral que ayuda a crear ambientes de escucha y compartir en armonía para todo e… | K62: Continuar garantizando la disponibilidad de los espacios físicos y logísticos requeridos para el desarrollo de las actividades programadas por el Comité de Convivencia Laboral.
A63: ADMINISTRATIVO FINANCIERO | B63: Administrativa y Financiera | C63: Administración de servicios de bienestar. | D63: Servicios de Bienestar: Capellanía, Psicoorientación, Enfermería, Biblioteca, Secretaría, Economía,Fotocopiadora, Transporte y Tienda Escolar | F63: 4 | G63: =IF(E63="","—",IF(F63>E63,"▲",IF(F63<E63,"▼","="))) -> — | H63: Se cuenta con personal competente para la prestación de servicios de bienestar conforme a las necesidades institucionales. | K63: Continuar fortaleciendo la prestación eficiente y oportuna de los servicios brindados por las dependencias mencionadas anteriormente, garantizando la calidad de la atención y la satisfacción de las ne…
A64: ADMINISTRATIVO FINANCIERO | B64: Administrativa y Financiera | C64: . Talento humano | D64: Conocimiento, apropiación y desempeño de los Perfiles de cargos y responsabilidades propias | F64: 4 | G64: =IF(E64="","—",IF(F64>E64,"▲",IF(F64<E64,"▼","="))) -> — | H64: Se cuenta con un cronograma de formación al personal.El personal vinculado participa de capacitaciones externas promovidas por la Inspectoría, ARL, SE… | K64: Continuar fomentando la participación activa del personal en los programas de formación y capacitación ofrecidos por la institución, así como en aquellos promovidos por entidades externas, con el fin …
A65: ADMINISTRATIVO FINANCIERO | B65: Administrativa y Financiera | C65: . Talento humano | D65: Selección, inducción y acompañamiento del personal nuevo que se vincula laboralmente a la Institución. | F65: 3 | G65: =IF(E65="","—",IF(F65>E65,"▲",IF(F65<E65,"▼","="))) -> — | H65: En las oficinas reposan toda la documentación pertinentes correspondientes a los procesos de selección del personal nuevo | K65: Continuar garantizando el cumplimiento de las funciones docentes, de acuerdo con la asignación académica establecida.Se sugiere que desde la coordinación académica haya más acompañamiento al docente n…
A66: ADMINISTRATIVO FINANCIERO | B66: Administrativa y Financiera | C66: . Talento humano | D66: Capacitación, actualización y formación humana, cristiana, salesiana y pedagógica del personal vinculado laboralmente a la Institución. | F66: 4 | G66: =IF(E66="","—",IF(F66>E66,"▲",IF(F66<E66,"▼","="))) -> — | H66: Los docentes y directiva poseen cronograma institucional donde asisten a las capacitaciones una vez por semana de las diferentes dependencias (Humana,… | K66: Seguir impulsando la asistencia y el compromiso del talento humano en los espacios de formación interna, al igual que en las ofertas de capacitación de organismos externos, buscando así potenciar sus …
A67: ADMINISTRATIVO FINANCIERO | B67: Administrativa y Financiera | C67: . Talento humano | D67: Asignación académica y responsabilidades de los educadores | F67: 4 | G67: =IF(E67="","—",IF(F67>E67,"▲",IF(F67<E67,"▼","="))) -> — | H67: Al inicio del año escolar, los coordinadores y directivos socializan las responsabilidades y asignaciones académicas de cada uno de los docentes | K67: Continuar garantizando el cumplimiento de las funciones docentes, de acuerdo con la asignación académica establecida.
A68: ADMINISTRATIVO FINANCIERO | B68: Administrativa y Financiera | C68: . Talento humano | D68: Evaluación de desempeño semestral y anual del personal vinculado laboralmente a la Institución. | F68: 4 | G68: =IF(E68="","—",IF(F68>E68,"▲",IF(F68<E68,"▼","="))) -> — | H68: Se realizan actividades de reconocimiento al personal que labora en la institución, donde se agradece y exalta su trabajo como la conmemoración del dí… | K68: Es importante que el personal de servicios generales posean un formato donde puedan autoevaluarse.
A69: ADMINISTRATIVO FINANCIERO | B69: Administrativa y Financiera | C69: . Talento humano | D69: Reconocimiento al personal que se destaca en el desempeño de sus responsabilidades. | F69: 4 | G69: =IF(E69="","—",IF(F69>E69,"▲",IF(F69<E69,"▼","="))) -> — | H69: Se realizan actividades de reconocimiento al personal que labora en la institución, donde se agradece y exalta su trabajo como la conmemoración del dí… | K69: Fortalecer los mecanismos de motivación del personal de la ENS mediante estrategias de reconocimiento público que destaquen su desempeño, responsabilidad y capacidad organizativa.
A70: ADMINISTRATIVO FINANCIERO | B70: Administrativa y Financiera | C70: . Talento humano | D70: Apoyo con recursos físicos y financieros para la organización y realización de la investigación educativa. | F70: 4 | G70: =IF(E70="","—",IF(F70>E70,"▲",IF(F70<E70,"▼","="))) -> — | H70: En el presupuesto institucional se destinan recursos financieros y se provee recursos físicos para la organización y realización del evento de investi… | K70: Continuar gestionando los recursos para dar cumplimiento a las actividades encaminadas a la producción y publicación del conocimiento.
A71: ADMINISTRATIVO FINANCIERO | B71: Administrativa y Financiera | C71: . Talento humano | D71: Apoyo con recursos para la producción y publicación del conocimiento. | F71: 4 | G71: =IF(E71="","—",IF(F71>E71,"▲",IF(F71<E71,"▼","="))) -> — | H71: El presupuesto de la institución contempla la asignación específica de fondos financieros y la provisión de los recursos físicos necesarios para la pl… | K71: Continuar gestionando los recursos para dar cumplimiento a las actividades encaminadas a la producción y publicación del conocimiento..
A72: ADMINISTRATIVO FINANCIERO | B72: Administrativa y Financiera | C72: Apoyo financiero y registros contables | D72: Presupuesto anual y Contabilidad mensual y anual de Ingresos y gastos | F72: 4 | G72: =IF(E72="","—",IF(F72>E72,"▲",IF(F72<E72,"▼","="))) -> — | H72: Elaboración del presupuesto anual conforme a las necesidades institucionales e indicadores económicos.Se lleva la contabilidad conforme a la legislaci… | K72: Continuar ejecutando los recursos conforme a lo presupuestado.Continuar manteniendo la gestión contable conforme a los lineamientos establecidos por la Comunidad
A73: ADMINISTRATIVO FINANCIERO | B73: Administrativa y Financiera | C73: Apoyo financiero y registros contables | D73: Costos educativos, pago de pensiones y cartera morosa. | F73: 3 | G73: =IF(E73="","—",IF(F73>E73,"▲",IF(F73<E73,"▼","="))) -> — | H73: Costos educativos aprobados mediante Resolución por la SEM-SOACHA.Contrato de prestación del servicio público educativo suscrito con el municipio de S… | K73: Diseñar, estructurar e implementar alternativas y estrategias de recaudo innovadoras que complementen las acciones actuales, con el fin de contrarrestar los altos índices de cartera morosa vigentes. S…
A74: PROCESO SOCIAL COMUNITARIO → Gestión Comunidad (10 componentes)
A75: SOCIAL COMUNITARIO | B75: Comunidad | C75: Accesibilidad | D75: Atención educativa a grupos o poblaciones en situación de vulnerabilidad | F75: 3 | G75: =IF(E75="","—",IF(F75>E75,"▲",IF(F75<E75,"▼","="))) -> — | H75: Remisiones a entidades externas como ICBF, EPS, comisaría Municipal cuando se observan situaciones que ponen en riesgo los derechos de los NNA | K75: Fortalecer el seguimiento a los casos remitidos a entidades externas.Continuar promoviendo estrategias de prevención y detección temprana de situaciones de riesgo.Optimizar los canales de comunicación…
A76: SOCIAL COMUNITARIO | B76: Comunidad | C76: Accesibilidad | D76: Atención educativa a necesidades y expectativas de los estudiantes. | F76: 4 | G76: =IF(E76="","—",IF(F76>E76,"▲",IF(F76<E76,"▼","="))) -> — | H76: Actas de seguimiento de atención realizadas por psicoorientación y coordinación de convivencia, registro en observadores de los estudiantes, citacione… | K76: Continuar con el seguimiento de las situaciones que se presentan con los estudiantes de manera oportuna. Fortalecer la participación y asistencia de las familias a las citaciones y procesos de seguimi…
A77: SOCIAL COMUNITARIO | B77: Comunidad | C77: Proyección, Participación y convivencia en la comunidad | D77: Organización, participación y realización del programa de “Escuela de Padres/Madres”. | F77: 4 | G77: =IF(E77="","—",IF(F77>E77,"▲",IF(F77<E77,"▼","="))) -> — | H77: Actas de Escuela de Padres, piezas gráficas de convocatoria, formato de asistencia diligenciado por los padres de familia, registro fotográfico. | K77: Incrementar la asistencia y participación de las familias en las Escuela de Padres. Continuar en la planeación y gestión con entidades externas y profesionales para la orientación de los talleres.
A78: SOCIAL COMUNITARIO | B78: Comunidad | C78: Proyección, Participación y convivencia en la comunidad | D78: Oferta y demanda del servicio educativo del Colegio María Auxiliadora. | F78: 4 | G78: =IF(E78="","—",IF(F78>E78,"▲",IF(F78<E78,"▼","="))) -> — | H78: Implementación del énfasis tecnológico que ofrecerá el Colegio Maria Auxiliadora a la comunidad.Representaciones externas a nivel deportivo, cultural … | K78: Continuar con la implementación del énfasis tecnológico que ofrecerá el Colegio Maria Auxiliadora a la comunidad. Continuar con la representación del colegio a nivel deportivo, cultural y académico fr…
A79: SOCIAL COMUNITARIO | B79: Comunidad | C79: Proyección, Participación y convivencia en la comunidad | D79: Estrategias que educan al uso correcto y adecuado de los espacios de la planta física y de los recursos. | F79: 3 | G79: =IF(E79="","—",IF(F79>E79,"▲",IF(F79<E79,"▼","="))) -> — | H79: Charlas en buenos días sobre el cuidado de la casa común. Espacios de reflexión en direcciones de curso sobre el adecuado uso de los recursos y la pla… | K79: Fortalecer la participación de toda la comunidad educativa en las actividades ambientales propuestas. Continuar en la búsqueda de estrategias que permitan generar conciencia del cuidado de la planta f…
A80: SOCIAL COMUNITARIO | B80: Comunidad | C80: Proyección, Participación y convivencia en la comunidad | D80: Organización, realización y seguimiento del Proyecto de Servicio Social de los estudiantes. | F80: 4 | G80: =IF(E80="","—",IF(F80>E80,"▲",IF(F80<E80,"▼","="))) -> — | H80: Proyecto de servicio socialActa de reunión con padres de familia al inicio del año escolar Asignación de responsabilidades a los estudiantes y campos … | K80: Ampliar los campos de ejecución de servicio social con énfasis en el trabajo comunitario como hospitales, comisarías, colegios, entre otras.
A81: SOCIAL COMUNITARIO | B81: Comunidad | C81: Proyección, Participación y convivencia en la comunidad | D81: Participación de los estudiantes en actividades de mejoramiento de la calidad educativa. | F81: 4 | G81: =IF(E81="","—",IF(F81>E81,"▲",IF(F81<E81,"▼","="))) -> — | H81: Pautas de dirección de curso, espacios de buenos días dirigidos por el alto gobierno escolar, liderazgo y organización de los estudiantes de grado 11°… | K81: Diversificar las estrategias y temáticas abordadas en los buenos días y direcciones de curso.Incrementar la participación de estudiantes de diferentes cursos en la organización y liderazgo de activida…
A82: SOCIAL COMUNITARIO | B82: Comunidad | C82: Prevención de riesgos. | D82: Organización y ejecución del Proyecto de Prevención de riesgos físicos y de desastres; programas o planes de seguridad, y simulacros de evacuación. | F82: 4 | G82: =IF(E82="","—",IF(F82>E82,"▲",IF(F82<E82,"▼","="))) -> — | H82: Documento de plan de emergencia, donde se planea, asigna y evalua.Formato de los simulacros.El documento de favorabilidad de la oficina de gestión del… | K82: Continuar participando en las diferentes actividades y simulacros, teniendo en cuenta las recomendaciones dadas.
A83: SOCIAL COMUNITARIO | B83: Comunidad | C83: Prevención de riesgos. | D83: Estrategias educativas aplicadas, para prevención de riesgos psicosociales: Trata de personas, adicciones, consumo de sustancias psicoactivas o embriagantes, uso de internet, enfermedades de tipo sexual, embarazos, suicidio, violencia intrafamiliar, etc.) | F83: 3 | G83: =IF(E83="","—",IF(F83>E83,"▲",IF(F83<E83,"▼","="))) -> — | H83: Direcciones de cursoTalleres de psicoorientación y coordinación de convivencia.Taller externo por “compañía Nosotras” | K83: Continuar buscando estrategias de prevención para los riesgos psicosociales que aquí se presentan.
A84: SOCIAL COMUNITARIO | B84: Comunidad | C84: Prevención de riesgos. | D84: Estrategias aplicadas en el aula e institución, que educan al cuidado del medio ambiente y reciclaje. | F84: 4 | G84: =IF(E84="","—",IF(F84>E84,"▲",IF(F84<E84,"▼","="))) -> — | H84: Pautas de dirección de curso.Actividades institucionales Elección de líderes ambientales. | K84: Pendiente la evaluación de los líderes ambientales del primer semestre.Continuar con las estrategias a traves de actividades para el cuidado del medio ambiente.
A85: PROCESO EVANGELIZADOR → Gestión Pastoral (propio salesiano) (12 componentes)
A86: EVANGELIZADOR | B86: Pastoral (propio salesiano) | C86: Formación en la fe | D86: Organización, participación y realización de los Retiros Espirituales en la comunidad educativa. | F86: 4 | G86: =IF(E86="","—",IF(F86>E86,"▲",IF(F86<E86,"▼","="))) -> — | H86: fotos, listados, evaluaciones y material que reposa en carpeta del área en drive. | K86: Como una oportunidad de mejora se propone favorecer y abrir espacios para el crecimiento en la fe a nivel familiar. La organización y ejecución de algunas de las actividades desarrolladas por la entid…
A87: EVANGELIZADOR | B87: Pastoral (propio salesiano) | C87: Formación en la fe | D87: Programación y realización de la Educación Religiosa Escolar y la Catequesis. | F87: 4 | G87: =IF(E87="","—",IF(F87>E87,"▲",IF(F87<E87,"▼","="))) -> — | H87: Estructura curricular y planeaciones de ERE, guías de preparación de los sacramentos de Primera Comunión y confirmación. | K87: Continuar fortaleciendo las clases de ERE, como espacio que garantice la reflexión crítica de la realidad y los contextos desde la perspectiva de la fe cristiana.
A88: EVANGELIZADOR | B88: Pastoral (propio salesiano) | C88: Formación en la fe | D88: Ambiente de piedad y amor Mariano | F88: 4 | G88: =IF(E88="","—",IF(F88>E88,"▲",IF(F88<E88,"▼","="))) -> — | H88: Talleres Florecillas.Archivo fotográfico del mes de mayo.Guión del rosario.Guion de la Novena a Maria Auxiliadora,Guión de la celebración eucarística.… | K88: Continuar fortaleciendo el sentido y vivencia profunda de la la espiritualidad mariana durante la planeación, preparación y ejecución de cada uno de los momentos que hacen parte del Mes de Mayo y las …
A89: EVANGELIZADOR | B89: Pastoral (propio salesiano) | C89: Formación en la fe | D89: Preparación, participación y actitud de fe en las celebraciones de los sacramentos de la Eucaristía y de la Reconciliación. | F89: 3 | G89: =IF(E89="","—",IF(F89>E89,"▲",IF(F89<E89,"▼","="))) -> — | H89: El cronograma de Eucaristías y organización propuesta desde coordinación de pastoral, Guiones de Eucaristías realizados por los directores de grupo. | K89: Fortalecer por cursos la formación y preparación de estudiantes que se encarguen de manera específica de las lecturas durante las celebraciones eucarísticas. Continuar fortaleciendo la participación c…
A90: EVANGELIZADOR | B90: Pastoral (propio salesiano) | C90: Formación en la fe | D90: Formación y ambiente de vida de fe en la Comunidad Educativa. | F90: 3 | G90: =IF(E90="","—",IF(F90>E90,"▲",IF(F90<E90,"▼","="))) -> — | H90: CronogramaListas de asistencia PlaneacionesGuiones y guías de celebraciones y formación en la fe.Buenos días.Los retiros espirituales | K90: Se ve necesario fortalecer la dimensión espiritual de la comunidad educativa, para que sus acciones correspondan con la intención formativa de la espiritualidad salesiana.
A91: EVANGELIZADOR | B91: Pastoral (propio salesiano) | C91: Formación en la fe | D91: Organización, preparación y realización de los “Buenos días” a nivel general y por cursos. | F91: 4 | G91: =IF(E91="","—",IF(F91>E91,"▲",IF(F91<E91,"▼","="))) -> — | H91: Cronograma institucionalRecordatorio semanal en el Whatsapp del equipo docente por parte del coordinador de convivencia.Guías con orientaciones a los … | K91: Abrir espacios en el tiempo de buenos días, para favorecer el protagonismo de los estudiantes, especialmente de las animadoras y miembros del MJS.
A92: EVANGELIZADOR | B92: Pastoral (propio salesiano) | C92: Formación en la fe | D92: Preparación y participación de animadoras líderes del Movimiento Juvenil Salesiano (MJS). | F92: 4 | G92: =IF(E92="","—",IF(F92>E92,"▲",IF(F92<E92,"▼","="))) -> — | H92: Plan formativoRegistros de asistenciaRegistros de planeación de sesiones. | K92: Se hace necesario fortalecer la formación en liderazgo y el protagonismo juvenil de los estudiantes en las actividades pastorales de la institución.
A93: EVANGELIZADOR | B93: Pastoral (propio salesiano) | C93: Formación en la fe | D93: Preparación, participación y realización de la “Propuesta Pastoral” en los cursos y ambiente institucional. | F93: 4 | G93: =IF(E93="","—",IF(F93>E93,"▲",IF(F93<E93,"▼","="))) -> — | H93: Cronograma institucional y Recordatorios por parte de la coordinación de pastoral sobre los diferentes episodios de la Propuesta Pastoral | K93: Seguir fortaleciendo e interiorizando la intención pastoral de cada una de las etapas de la propuesta pastoral.
A94: EVANGELIZADOR | B94: Pastoral (propio salesiano) | C94: Formación de “Buenos Cristianos y Honestas Ciudadanas”. | D94: Organización, participación y ejecución de Proyectos de Solidaridad, para las personas más necesitadas. | F94: 2 | G94: =IF(E94="","—",IF(F94>E94,"▲",IF(F94<E94,"▼","="))) -> — | H94: Borradores de propuestas. | K94: Está por establecer un trabajo conjunto con la Diòcesis de Soacha y parroquias cercanas, con el fin de que los estudiantes se acerquen y procuren dar respuesta a las necesidades propias de nuestra Igl…
A95: EVANGELIZADOR | B95: Pastoral (propio salesiano) | C95: Formación de “Buenos Cristianos y Honestas Ciudadanas”. | D95: Ambiente educativo de “Buenos Cristianos y Honestos Ciudadanos”. | F95: 3 | G95: =IF(E95="","—",IF(F95>E95,"▲",IF(F95<E95,"▼","="))) -> — | H95: Actas, talleres y guiones de dirección de curso. | K95: Continuar fortaleciendo el trabajo transversal con todas las áreas. junto con los valores del carisma salesiano en todos los espacios y con toda la comunidad.
A96: EVANGELIZADOR | B96: Pastoral (propio salesiano) | C96: Formación de “Buenos Cristianos y Honestas Ciudadanas”. | D96: Organización y orientación adecuada del proyecto de vida de los estudiantes | F96: 4 | G96: =IF(E96="","—",IF(F96>E96,"▲",IF(F96<E96,"▼","="))) -> — | H96: Actividades en clase de ERE | K96: Continuar trabajando el proyecto de vida en todos los grados para incentivar en los estudiantes la valoración de esta herramiento de crecimiento integral.
A97: EVANGELIZADOR | B97: Pastoral (propio salesiano) | C97: Proyecto de Formación Conjunta | D97: Organización, participación y realización de la “Escuela de formación conjunta salesiana”, para la formación humana, cristiana y salesiana del personal. | F97: 4 | G97: =IF(E97="","—",IF(F97>E97,"▲",IF(F97<E97,"▼","="))) -> — | H97: Actas de reunión de educadores | K97: Los docentes han participado activamente en los espacios formativos del Proyecto Laicos que busca fortalecer su identidad carismática y compromiso educativo. Sin embargo hay preocupación por una mayor…
A98: PROCESO GESTIÓN DE CALIDAD → Gestión Calidad (transverso) (5 componentes)
A99: GESTIÓN DE CALIDAD | B99: Calidad (transverso) | C99: Sistema Gestión de Calidad | D99: La implicación responsable de todos los educadores y personal administrativo y de servicios generales. | F99: 3 | G99: =IF(E99="","—",IF(F99>E99,"▲",IF(F99<E99,"▼","="))) -> — | H99: Actas y formatos de asistencia de capacitación docente y del personal de servicios y administrativo | K99: Generar más espacios de capacitación y formación de conciencia frente a la implicación responsable de los trabajadores en el cumplimiento del SGC como parte fundamental para la prestación del servicio…
A100: GESTIÓN DE CALIDAD | B100: Calidad (transverso) | C100: Sistema Gestión de Calidad | D100: El manejo adecuado y simplificado de documentos y registros | F100: 3 | G100: =IF(E100="","—",IF(F100>E100,"▲",IF(F100<E100,"▼","="))) -> — | H100: Actas de reuniones del Equipo de calidad con la aprobación de ajustes e implementación de nuevos formatos y documentos Implementación de formatos | K100: Continuar trabajando en el correcto diligenciamiento de los formatos e implementación de los documentos en pro del desarrollo favorable de los procesos en la prestación del servicio educativo.
A101: GESTIÓN DE CALIDAD | B101: Calidad (transverso) | C101: Sistema Gestión de Calidad | D101: Realización de las auditorías internas según el procedimiento correspondiente | F101: 3 | G101: =IF(E101="","—",IF(F101>E101,"▲",IF(F101<E101,"▼","="))) -> — | H101: Planeación, apertura, ejecución y cierre de la primera auditoría interna 2026 | K101: Continuar con el proceso de capacitación de auditores internos de acuerdo a la legislación vigente para el ámbito educativo.Continuar el proceso de seguimiento de los resultados arrojados en la primer…
A102: GESTIÓN DE CALIDAD | B102: Calidad (transverso) | C102: Sistema Gestión de Calidad | D102: Favorecer la autoevaluación institucional de los procesos de direccionamiento, misionales y de apoyo para asegurar y satisfacer la prestación del servicio educativo | F102: 4 | G102: =IF(E102="","—",IF(F102>E102,"▲",IF(F102<E102,"▼","="))) -> — | H102: Planeacion y ejecucion de jornada pedagógica de autoevaluación institucional 2026-A (acta, formatos de autoevaluación institucional y evaluación de de… | K102: Hacer revisión juiciosa de las acciones de mejora para la planeación y desarrollo de las acciones propias de cada proceso con el propósito de lograr las mejoras esperadas en la autoevaluación de final…
A103: GESTIÓN DE CALIDAD | B103: Calidad (transverso) | C103: Sistema Gestión de Calidad | D103: Compartir por drive la carpeta digital al equipo de educadores, con los formatos correspondientes a la autoevaluación institucional que están en proceso tales como: el Plan de Mejoramiento Institucional, guía 34, Matriz de riesgos y demás que faciliten el seguimiento a las acciones que están a su cargo. | F103: 4 | G103: =IF(E103="","—",IF(F103>E103,"▲",IF(F103<E103,"▼","="))) -> — | H103: Carpeta DRIVE (Jornada pedagógica junio 19 2026) que contiene los documentos y formatos que se trabajaron durante la jornada pedagógica | K103: Continuar revisando el correcto diligenciamiento de los formatos propios del proceso de autoevaluación institucional y la ejecución de las oportunidades de mejora en pro de generar un buen cierre en l…

Sheet Tablero_Perfil
A1: Perfil institucional de calidad — consolidado (auto)
A3: Proceso | B3: N.º comp. | C3: Nivel 1 | D3: Nivel 2 | E3: Nivel 3 | F3: Nivel 4 | G3: Media I-2026
A4: DIRECTIVO | B4: =COUNTIF(Matriz_Revisión!A2:A103,"DIRECTIVO") -> 25 | C4: =COUNTIFS(Matriz_Revisión!A2:A103,"DIRECTIVO",Matriz_Revisión!F2:F103,1) -> 0 | D4: =COUNTIFS(Matriz_Revisión!A2:A103,"DIRECTIVO",Matriz_Revisión!F2:F103,2) -> 0 | E4: =COUNTIFS(Matriz_Revisión!A2:A103,"DIRECTIVO",Matriz_Revisión!F2:F103,3) -> 8 | F4: =COUNTIFS(Matriz_Revisión!A2:A103,"DIRECTIVO",Matriz_Revisión!F2:F103,4) -> 17 | G4: =IFERROR(AVERAGEIF(Matriz_Revisión!A2:A103,"DIRECTIVO",Matriz_Revisión!F2:F103),"—") -> 3.68
A5: ACADÉMICO PEDAGÓGICO | B5: =COUNTIF(Matriz_Revisión!A2:A103,"ACADÉMICO PEDAGÓGICO") -> 24 | C5: =COUNTIFS(Matriz_Revisión!A2:A103,"ACADÉMICO PEDAGÓGICO",Matriz_Revisión!F2:F103,1) -> 0 | D5: =COUNTIFS(Matriz_Revisión!A2:A103,"ACADÉMICO PEDAGÓGICO",Matriz_Revisión!F2:F103,2) -> 3 | E5: =COUNTIFS(Matriz_Revisión!A2:A103,"ACADÉMICO PEDAGÓGICO",Matriz_Revisión!F2:F103,3) -> 3 | F5: =COUNTIFS(Matriz_Revisión!A2:A103,"ACADÉMICO PEDAGÓGICO",Matriz_Revisión!F2:F103,4) -> 18 | G5: =IFERROR(AVERAGEIF(Matriz_Revisión!A2:A103,"ACADÉMICO PEDAGÓGICO",Matriz_Revisión!F2:F103),"—") -> 3.625
A6: ADMINISTRATIVO FINANCIERO | B6: =COUNTIF(Matriz_Revisión!A2:A103,"ADMINISTRATIVO FINANCIERO") -> 20 | C6: =COUNTIFS(Matriz_Revisión!A2:A103,"ADMINISTRATIVO FINANCIERO",Matriz_Revisión!F2:F103,1) -> 0 | D6: =COUNTIFS(Matriz_Revisión!A2:A103,"ADMINISTRATIVO FINANCIERO",Matriz_Revisión!F2:F103,2) -> 0 | E6: =COUNTIFS(Matriz_Revisión!A2:A103,"ADMINISTRATIVO FINANCIERO",Matriz_Revisión!F2:F103,3) -> 4 | F6: =COUNTIFS(Matriz_Revisión!A2:A103,"ADMINISTRATIVO FINANCIERO",Matriz_Revisión!F2:F103,4) -> 16 | G6: =IFERROR(AVERAGEIF(Matriz_Revisión!A2:A103,"ADMINISTRATIVO FINANCIERO",Matriz_Revisión!F2:F103),"—") -> 3.8
A7: SOCIAL COMUNITARIO | B7: =COUNTIF(Matriz_Revisión!A2:A103,"SOCIAL COMUNITARIO") -> 10 | C7: =COUNTIFS(Matriz_Revisión!A2:A103,"SOCIAL COMUNITARIO",Matriz_Revisión!F2:F103,1) -> 0 | D7: =COUNTIFS(Matriz_Revisión!A2:A103,"SOCIAL COMUNITARIO",Matriz_Revisión!F2:F103,2) -> 0 | E7: =COUNTIFS(Matriz_Revisión!A2:A103,"SOCIAL COMUNITARIO",Matriz_Revisión!F2:F103,3) -> 3 | F7: =COUNTIFS(Matriz_Revisión!A2:A103,"SOCIAL COMUNITARIO",Matriz_Revisión!F2:F103,4) -> 7 | G7: =IFERROR(AVERAGEIF(Matriz_Revisión!A2:A103,"SOCIAL COMUNITARIO",Matriz_Revisión!F2:F103),"—") -> 3.7
A8: EVANGELIZADOR | B8: =COUNTIF(Matriz_Revisión!A2:A103,"EVANGELIZADOR") -> 12 | C8: =COUNTIFS(Matriz_Revisión!A2:A103,"EVANGELIZADOR",Matriz_Revisión!F2:F103,1) -> 0 | D8: =COUNTIFS(Matriz_Revisión!A2:A103,"EVANGELIZADOR",Matriz_Revisión!F2:F103,2) -> 1 | E8: =COUNTIFS(Matriz_Revisión!A2:A103,"EVANGELIZADOR",Matriz_Revisión!F2:F103,3) -> 3 | F8: =COUNTIFS(Matriz_Revisión!A2:A103,"EVANGELIZADOR",Matriz_Revisión!F2:F103,4) -> 8 | G8: =IFERROR(AVERAGEIF(Matriz_Revisión!A2:A103,"EVANGELIZADOR",Matriz_Revisión!F2:F103),"—") -> 3.5833333
A9: GESTIÓN DE CALIDAD | B9: =COUNTIF(Matriz_Revisión!A2:A103,"GESTIÓN DE CALIDAD") -> 5 | C9: =COUNTIFS(Matriz_Revisión!A2:A103,"GESTIÓN DE CALIDAD",Matriz_Revisión!F2:F103,1) -> 0 | D9: =COUNTIFS(Matriz_Revisión!A2:A103,"GESTIÓN DE CALIDAD",Matriz_Revisión!F2:F103,2) -> 0 | E9: =COUNTIFS(Matriz_Revisión!A2:A103,"GESTIÓN DE CALIDAD",Matriz_Revisión!F2:F103,3) -> 3 | F9: =COUNTIFS(Matriz_Revisión!A2:A103,"GESTIÓN DE CALIDAD",Matriz_Revisión!F2:F103,4) -> 2 | G9: =IFERROR(AVERAGEIF(Matriz_Revisión!A2:A103,"GESTIÓN DE CALIDAD",Matriz_Revisión!F2:F103),"—") -> 3.4
A10: TOTAL | B10: =SUM(B4:B9) -> 96 | C10: =COUNTIF(Matriz_Revisión!F2:F103,1) -> 0 | D10: =COUNTIF(Matriz_Revisión!F2:F103,2) -> 4 | E10: =COUNTIF(Matriz_Revisión!F2:F103,3) -> 24 | F10: =COUNTIF(Matriz_Revisión!F2:F103,4) -> 68 | G10: =IFERROR(AVERAGE(Matriz_Revisión!F2:F103),"—") -> 3.6666667
A12: Lectura: 71% de los componentes se autovaloran en nivel 4 y ninguno en nivel 1 — leer con cautela (efecto techo). El contraste con la evidencia externa (hoja Evidencia_Externa) es el núcleo de la revisión.

Sheet Evidencia_Externa
A1: Evidencia externa para triangular la autovaloración
A3: Saber 11 — puntaje por área (fuente: ICFES, reexpuesto por ICFES Analytics)
A4: Área | B4: 2023 | C4: 2024 | D4: 2025 | E4: Δ 2023–25
A5: Global | B5: 324.6 | C5: 316 | D5: 304.8 | E5: =D5-B5 -> -19.8
A6: Matemáticas | B6: 65.6 | C6: 61.9 | D6: 60.3 | E6: =D6-B6 -> -5.3
A7: Lectura Crítica | B7: 64.8 | C7: 64.9 | D7: 62.9 | E7: =D7-B7 -> -1.9
A8: Ciencias Naturales | B8: 63.6 | C8: 62.1 | D8: 59.6 | E8: =D8-B8 -> -4
A9: Sociales y Ciudadanas | B9: 63.4 | C9: 60.9 | D9: 58.4 | E9: =D9-B9 -> -5
A10: Inglés | B10: 71.4 | C10: 71.9 | D10: 69.2 | E10: =D10-B10 -> -2.2
A12: Contexto 2025
A13: Puntaje global 2025 | B13: 304,8
A14: Percentil nacional | B14: 88 (Top 12%)
A15: Puesto Soacha | B15: #5 de 113
A16: Valor agregado contextual | B16: +42,6 pts sobre lo esperado (262,2)
A17: vs promedio nacional | B17: +47,1 pts
A18: Estudiantes evaluados | B18: ≈25 (alta variabilidad entre cohortes)
A19: Fortalezas | B19: Inglés · Lectura Crítica
A20: Áreas foco | B20: C. Naturales · Sociales y Ciudadanas
A22: Matrícula (SIMAT) — evolución
A23: 2015 | B23: 2016 | C23: 2017 | D23: 2018 | E23: 2019 | F23: 2020 | G23: 2021 | H23: 2022 | I23: 2024
A24: 803 | B24: 683 | C24: 636 | D24: 595 | E24: 553 | F24: 470 | G24: 446 | H24: 425 | I24: 503
A26: 803 (2015) → piso 425 (2022) → 503 (2024). Grados 9–11 hoy 100% femeninos; preescolar/primaria mixtos: transición de identidad.
A29: Fuentes: ICFES Analytics (icfes-analytics.com) y MIAcademia (miacademia.ai), plataformas de terceros; puntajes por área = datos oficiales ICFES reexpuestos. Índices derivados (valor agregado, cuadrantes) son modelos propios, no causales. N≈25 → interpretar con cautela.

Sheet Transverso_Calidad
A1: Transverso de calidad — esqueleto del cuadro de mando (a definir en el PEI)
A2: Línea base precargada donde existe; metas, responsables y periodicidad se concretan con la ENSMA.
A4: Indicador | B4: Fuente | C4: Línea base | D4: Meta 2027 | E4: Responsable | F4: Periodicidad
A5: Saber 11 — puntaje global | B5: ICFES | C5: 304,8 (2025)
A6: Saber 11 — C. Naturales | B6: ICFES | C6: 59,6 (2025)
A7: Saber 11 — Sociales y Ciudadanas | B7: ICFES | C7: 58,4 (2025)
A8: Matrícula total | B8: SIMAT | C8: 503 (2024)
A9: Competencia digital docente (índice) | B9: Instrumento 1.2.5 | C9: 79,4 (2026)
A10: Brecha IA docente (interés−destreza) | B10: Instrumento 1.2.5 | C10: 23,2 (2026)
A11: % componentes autoeval. ≥ nivel 3 | B11: Autoevaluación Guía 34 | C11: ≈96% (I-2026)
A12: Cierre de oportunidades de mejora del PMI | B12: PMI / seguimiento | C12: (cargar)
A13: Uso de recursos virtuales/multimedia (aula) | B13: Autoeval. comp. · 1.2.5 | C13: Nivel 2 (I-2026)
A15: El transverso re-funda el proceso de Gestión de Calidad ya existente, re-anclado al horizonte nuevo (post-Normal, EPBM + media técnica) e incorporando innovación/tecnología como dimensión evaluable.

Sheet Notas_Método
B1: Notas de método, escala y pendientes
B3: Escala Guía 34 (autovaloración)
B4: 1 Existencia · 2 Pertinencia · 3 Apropiación · 4 Mejoramiento continuo.
B5: Semáforo de la matriz: 1 rojo · 2 naranja · 3 amarillo · 4 verde. Naranja claro = celda por diligenciar.
B6: Lo que falta para concluir
B7: • Autoevaluación del ciclo anterior (2025) → columna E de la matriz; habilita «Tendencia» y el contraste temporal del propio instrumento.
B8: • PMI del año anterior con corte de seguimiento → columna L (¿acción en PMI?) y cierre de oportunidades.
B9: • Ratificación de la autoevaluación por Consejo Académico/Directivo (traza de gobernanza).
B10: Hallazgos ya visibles
B11: • Autovaloración sesgada al alza: 71% en nivel 4, 0 en nivel 1 — efecto techo, coherente con el instrumento de competencias.
B12: • El componente «recursos didácticos virtuales y multimedia» se autopuntúa en 2: la institución ya reconoce la brecha tecnológica.
B13: • Saber 11 en descenso 3 años mientras el proceso académico se autovalora alto → principal tensión a resolver en el PEI.
B14: Encuadre EICIT propone y revisa; la autoevaluación es de la ENSMA. No se modifican sus valoraciones: se contrastan con evidencia y se priorizan.
